sheet2linkml/__init__.py
sheet2linkml/cli.py
sheet2linkml/model.py
sheet2linkml/source/__init__.py
sheet2linkml/source/gsheetmodel/__init__.py
sheet2linkml/source/gsheetmodel/datatype.py
sheet2linkml/source/gsheetmodel/entity.py
sheet2linkml/source/gsheetmodel/enum.py
sheet2linkml/source/gsheetmodel/gsheetmodel.py
sheet2linkml/source/gsheetmodel/mappings.py
sheet2linkml/terminologies/__init__.py
sheet2linkml/terminologies/service.py
sheet2linkml/terminologies/tccm/__init__.py
sheet2linkml/terminologies/tccm/api.py
sheet2linkml-1.3.0.dist-info/entry_points.txt
sheet2linkml-1.3.0.dist-info/LICENSE
sheet2linkml-1.3.0.dist-info/WHEEL
sheet2linkml-1.3.0.dist-info/METADATA
sheet2linkml-1.3.0.dist-info/RECORD
